kb_dashboard_tools/__init__.py
kb_dashboard_tools/auth.py
kb_dashboard_tools/kibana_client.py
kb_dashboard_tools/models.py
kb_dashboard_tools/results.py
kb_dashboard_tools-0.2.7.dist-info/WHEEL
kb_dashboard_tools-0.2.7.dist-info/METADATA
kb_dashboard_tools-0.2.7.dist-info/RECORD
