Metadata-Version: 2.3
Name: kb-dashboard-tools
Version: 0.2.7
Summary: Shared utilities for Kibana operations, authentication, and workflows
License: MIT
Classifier: Development Status :: 3 - Alpha
Classifier: Intended Audience :: Developers
Classifier: License :: OSI Approved :: MIT License
Classifier: Programming Language :: Python :: 3
Classifier: Programming Language :: Python :: 3.12
Classifier: Topic :: Software Development :: Code Generators
Requires-Dist: kb-dashboard-core==0.2.7
Requires-Dist: aiohttp>=3.13
Requires-Dist: prison>=0.2.1
Requires-Dist: pydantic>=2.12
Requires-Python: >=3.12
